{
    "@schema": "https://raw.githubusercontent.com/slicer/slicer/master/Modules/Loadable/Markups/Resources/Schema/markups-schema-v1.0.0.json#",
    "markups": [
        {
            "type": "Fiducial",
            "coordinateSystem": "LPS",
            "locked": false,
            "labelFormat": "%N-%d",
            "controlPoints": [
                {
                    "id": "1",
                    "label": "Target",
                    "description": "",
                    "associatedNodeID": "vtkMRMLScalarVolumeNode1",
                    "position": [-502.28654124022207, -375.70607133577678, -167.26159089994224],
                    "orientation": [-1.0, -0.0, -0.0, -0.0, -1.0, -0.0, 0.0, 0.0, 1.0],
                    "selected": true,
                    "locked": false,
                    "visibility": true,
                    "positionStatus": "defined"
                },
                {
                    "id": "2",
                    "label": "Entry",
                    "description": "",
                    "associatedNodeID": "vtkMRMLScalarVolumeNode1",
                    "position": [-476.3655401864016, -375.7495904586639, -150.3460687700911],
                    "orientation": [-1.0, -0.0, -0.0, -0.0, -1.0, -0.0, 0.0, 0.0, 1.0],
                    "selected": true,
                    "locked": false,
                    "visibility": true,
                    "positionStatus": "defined"
                }
            ],
            "display": {
                "visibility": true,
                "opacity": 1.0,
                "color": [0.4, 1.0, 1.0],
                "selectedColor": [0.23529411764705883, 1.0, 0.06274509803921569],
                "propertiesLabelVisibility": false,
                "pointLabelsVisibility": true,
                "textScale": 3.0,
                "glyphType": "Sphere3D",
                "glyphScale": 1.0,
                "glyphSize": 5.0,
                "useGlyphScale": true,
                "sliceProjection": false,
                "sliceProjectionUseFiducialColor": true,
                "sliceProjectionOutlinedBehindSlicePlane": false,
                "sliceProjectionColor": [1.0, 1.0, 1.0],
                "sliceProjectionOpacity": 0.6,
                "lineThickness": 0.2,
                "lineColorFadingStart": 1.0,
                "lineColorFadingEnd": 10.0,
                "lineColorFadingSaturation": 1.0,
                "lineColorFadingHueOffset": 0.0,
                "handlesInteractive": false,
                "snapMode": "toVisibleSurface"
            }
        }
    ]
}